{"Blocks":{"AHJ":{"Att":{"Annotative":false,"Dynamic":false,"Explode":true,"InsUnit":0,"ScaleUniformly":false},"Previews":{"240_64_64_1":{"Checksum":"945cacad2857a71b6bbf9856da15a5cfa75d9d80","URL":"one-dot2.dwg.AHJ.240_64_64_1.png"}}}},"Header":{"Att":{"Annotative":false,"Dynamic":false,"Explode":true,"GeoLoc":{"CSId":"","Has":false},"ModifiedTime":1707859240,"ScaleUniformly":false,"annotativeDwg":false,"insunits":1},"Checksum":"8ac7dc98d2ab15a49c553f548235ad662b1e2979","Preview":{"Checksum":"c4297a32046d755ce36a8f84011906985ab89456","URL":"one-dot2.dwg.png"}}}